twittier/__init__.py
twittier/__main__.py
twittier/lucky_draw/__init__.py
twittier/lucky_draw/lucky_draw.py
twittier/status_dumper/__init__.py
twittier/status_dumper/_types.py
twittier/status_dumper/status_dumper.py
twittier-0.1.0.dist-info/LICENSE
twittier-0.1.0.dist-info/METADATA
twittier-0.1.0.dist-info/WHEEL
twittier-0.1.0.dist-info/top_level.txt
twittier-0.1.0.dist-info/RECORD
