Metadata-Version: 2.1
Name: twittier
Version: 0.1.0
Summary: A tool to parse twitter http requests.
Home-page: https://github.com/qiujiangkun/twittier
Author: qiujiangkun
Author-email: qjk2001@gmail.com
Project-URL: Bug Tracker, https://github.com/qiujiangkun/twittier/issues
Classifier: Programming Language :: Python :: 3
Classifier: License :: OSI Approved :: MIT License
Classifier: Operating System :: OS Independent
Requires-Python: >=3.6
License-File: LICENSE
